mhpp/__init__.py
mhpp/config.py
mhpp/loggers.py
mhpp/utils.py
mhpp/cli/__init__.py
mhpp/cli/cmd_args.py
mhpp/components/__init__.py
mhpp/components/ingest_data.py
mhpp/components/score.py
mhpp/components/train.py
mhpp-0.3.0.dist-info/METADATA
mhpp-0.3.0.dist-info/WHEEL
mhpp-0.3.0.dist-info/entry_points.txt
mhpp-0.3.0.dist-info/top_level.txt
mhpp-0.3.0.dist-info/RECORD
