Metadata-Version: 2.1
Name: mhpp
Version: 0.3.0
Summary: A median house price prediction project to demonstrate packaging.
Requires-Dist: scipy
Requires-Dist: numpy
Requires-Dist: pandas
Requires-Dist: scikit-learn
Provides-Extra: interactive
Requires-Dist: matplotlib ; extra == 'interactive'
Requires-Dist: seaborn ; extra == 'interactive'
Requires-Dist: jupyter ; extra == 'interactive'
